AUTHORS.rst
CHANGELOG.rst
LICENSE
MANIFEST.in
README.rst
setup.py
django_fast_gfk.egg-info/PKG-INFO
django_fast_gfk.egg-info/SOURCES.txt
django_fast_gfk.egg-info/dependency_links.txt
django_fast_gfk.egg-info/not-zip-safe
django_fast_gfk.egg-info/requires.txt
django_fast_gfk.egg-info/top_level.txt
fast_gfk/__init__.py
fast_gfk/tests/__init__.py
fast_gfk/tests/manage.py
fast_gfk/tests/models.py
fast_gfk/tests/test_function.py
fast_gfk/tests/requirements/111.txt
fast_gfk/tests/settings/111.py
fast_gfk/tests/settings/__init__.py