Metadata-Version: 1.1
Name: django-fast-gfk
Version: 0.1
Summary: Do Django generic foreign key lookups in one query
Home-page: http://github.com/praekelt/django-fast-gfk
Author: Praekelt Consulting
Author-email: dev@praekelt.com
License: BSD
Platform: UNKNOWN
Classifier: Programming Language :: Python
Classifier: License :: OSI Approved :: BSD License
Classifier: Operating System :: OS Independent
Classifier: Framework :: Django
Classifier: Intended Audience :: Developers
Classifier: Topic :: Internet :: WWW/HTTP :: Dynamic Content
